Workbook

Sheet Executive Dashboard
A1: Retail Intelligence — Executive Performance Dashboard
A2: Scope: 9,994 Retail Transactions | Date Range: 2014-01-03 to 2017-12-30 | Source: Cleaned Tableau Sample Superstore Dataset
A4: 1. EXECUTIVE KPI SCORECARD (FORMULA-DRIVEN)
A5: Metric Description | B5: Calculation / Formula Logic | C5: Excel Formula Result | D5: Verified Value | E5: Status
A6: Total Net Sales | B6: SUM('Order Data'!Sales) | C6: =SUM('Order Data'!R2:R9995) | D6: $2,297,200.86 | E6: VERIFIED
A7: Total Net Profit | B7: SUM('Order Data'!Profit) | C7: =SUM('Order Data'!U2:U9995) | D7: $286,397.02 | E7: VERIFIED
A8: Overall Profit Margin | B8: Total Profit / Total Sales | C8: =IF(C6=0, 0, C7/C6) | D8: 12.47% | E8: VERIFIED
A9: Total Line Items Count | B9: COUNT('Order Data'!Row_ID) | C9: =COUNT('Order Data'!A2:A9995) | D9: 9,994 | E9: VERIFIED
A10: Total Physical Units Sold | B10: SUM('Order Data'!Quantity) | C10: =SUM('Order Data'!S2:S9995) | D10: 37,873 | E10: VERIFIED
A11: Distinct Order Count | B11: Unique Order ID Count | C11: 5009 | D11: 5,009 | E11: VERIFIED
A12: Unique Customer Count | B12: Unique Customer ID Count | C12: 793 | D12: 793 | E12: VERIFIED
A13: Average Order Value (AOV) | B13: Total Sales / Distinct Orders | C13: =C6/C11 | D13: $458.61 | E13: VERIFIED
A14: Total Loss Dollars | B14: SUMIF('Order Data'!Profit, '<0') | C14: =SUMIF('Order Data'!U2:U9995, "<0") | D14: -$156,131.29 | E14: VERIFIED
A15: Loss-Making Line Items Count | B15: COUNTIF('Order Data'!Profit, '<0') | C15: =COUNTIF('Order Data'!U2:U9995, "<0") | D15: 1,871 | E15: VERIFIED
A16: Loss-Making Line Item Share | B16: Loss Items / Total Items | C16: =C15/C9 | D16: 18.72% | E16: VERIFIED
A17: Net-Sales-Weighted Discount Proxy | B17: SUMPRODUCT(Sales, Discount) / Total Sales | C17: =SUMPRODUCT('Order Data'!R2:R9995, 'Order Data'!T2:T9995)/C6 | D17: 14.04% | E17: VERIFIED
A18: Simple Average Discount | B18: AVERAGE('Order Data'!Discount) | C18: =AVERAGE('Order Data'!T2:T9995) | D18: 15.62% | E18: VERIFIED
A21: 2. STRATEGIC GOVERNANCE PRINCIPLES (EVIDENCE-BACKED)
A22: 1. THE 20% DISCOUNT BREAKEVEN CLIFF: In this dataset, transactions discounted up to 20% remain healthy (11.6% to 29.8% margin). Past 20%, margins collapse into severe aggregate losses (-10.1% to -119.2%).
A23: 2. UNPROFITABLE SUBCATEGORIES: Tables (-$17.7K net loss) and Bookcases (-$3.5K net loss) are chronic loss leaders. They should be converted to bundle-only pricing with high-margin items rather than discounted standalone.
A24: 3. HIGH-VOLUME LOSS ACCOUNTS: Customer Decile 10 accounts buy $278K of product at an average discount of 37.1%, causing -$65.8K in cumulative net losses. Re-pricing these accounts with margin floors recovers profit without cutting sales.
A25: 4. REGIONAL DISPARITY: Central region margin is only 7.9% compared to West's 14.9%, driven by severe local discounting in Texas (-$25.7K loss) and Illinois (-$12.6K loss).

Sheet Order Data
A1: Row Id | B1: Order Id | C1: Order Date | D1: Ship Date | E1: Ship Mode | F1: Customer Id | G1: Customer Name | H1: Segment | I1: Country | J1: City | K1: State | L1: Postal Code | M1: Region | N1: Product Id | O1: Category | P1: Sub Category | Q1: Product Name | R1: Sales | S1: Quantity | T1: Discount | U1: Profit | V1: Shipping Days | W1: Order Year | X1: Order Quarter | Y1: Order Year Month | Z1: Discount Band | AA1: Is Profitable | AB1: Is Loss | AC1: Unit Price | AD1: Line Profit Margin
A2: 1 | B2: CA-2016-152156 | C2: 2016-11-08 | D2: 2016-11-11 | E2: Second Class | F2: CG-12520 | G2: Claire Gute | H2: Consumer | I2: United States | J2: Henderson | K2: Kentucky | L2: 42420 | M2: South | N2: FUR-BO-10001798 | O2: Furniture | P2: Bookcases | Q2: Bush Somerset Collection Bookcase | R2: 261.96 | S2: 2 | T2: 0 | U2: 41.9136 | V2: 3 | W2: 2016 | X2: 2016Q4 | Y2: 2016-11 | Z2: 0% (No Discount) | AA2: TRUE | AB2: FALSE | AC2: 130.98 | AD2: 0.16
A3: 2 | B3: CA-2016-152156 | C3: 2016-11-08 | D3: 2016-11-11 | E3: Second Class | F3: CG-12520 | G3: Claire Gute | H3: Consumer | I3: United States | J3: Henderson | K3: Kentucky | L3: 42420 | M3: South | N3: FUR-CH-10000454 | O3: Furniture | P3: Chairs | Q3: Hon Deluxe Fabric Upholstered Stacking Chairs, Rounded Back | R3: 731.94 | S3: 3 | T3: 0 | U3: 219.582 | V3: 3 | W3: 2016 | X3: 2016Q4 | Y3: 2016-11 | Z3: 0% (No Discount) | AA3: TRUE | AB3: FALSE | AC3: 243.98 | AD3: 0.3
A4: 3 | B4: CA-2016-138688 | C4: 2016-06-12 | D4: 2016-06-16 | E4: Second Class | F4: DV-13045 | G4: Darrin Van Huff | H4: Corporate | I4: United States | J4: Los Angeles | K4: California | L4: 90036 | M4: West | N4: OFF-LA-10000240 | O4: Office Supplies | P4: Labels | Q4: Self-Adhesive Address Labels for Typewriters by Universal | R4: 14.62 | S4: 2 | T4: 0 | U4: 6.8714 | V4: 4 | W4: 2016 | X4: 2016Q2 | Y4: 2016-06 | Z4: 0% (No Discount) | AA4: TRUE | AB4: FALSE | AC4: 7.31 | AD4: 0.47
A5: 4 | B5: US-2015-108966 | C5: 2015-10-11 | D5: 2015-10-18 | E5: Standard Class | F5: SO-20335 | G5: Sean O'Donnell | H5: Consumer | I5: United States | J5: Fort Lauderdale | K5: Florida | L5: 33311 | M5: South | N5: FUR-TA-10000577 | O5: Furniture | P5: Tables | Q5: Bretford CR4500 Series Slim Rectangular Table | R5: 957.5775 | S5: 5 | T5: 0.45 | U5: -383.031 | V5: 7 | W5: 2015 | X5: 2015Q4 | Y5: 2015-10 | Z5: 30.1% - 50% | AA5: FALSE | AB5: TRUE | AC5: 348.21 | AD5: -0.4
A6: 5 | B6: US-2015-108966 | C6: 2015-10-11 | D6: 2015-10-18 | E6: Standard Class | F6: SO-20335 | G6: Sean O'Donnell | H6: Consumer | I6: United States | J6: Fort Lauderdale | K6: Florida | L6: 33311 | M6: South | N6: OFF-ST-10000760 | O6: Office Supplies | P6: Storage | Q6: Eldon Fold 'N Roll Cart System | R6: 22.368 | S6: 2 | T6: 0.2 | U6: 2.5164 | V6: 7 | W6: 2015 | X6: 2015Q4 | Y6: 2015-10 | Z6: 10.1% - 20% | AA6: TRUE | AB6: FALSE | AC6: 13.98 | AD6: 0.1125
A7: 6 | B7: CA-2014-115812 | C7: 2014-06-09 | D7: 2014-06-14 | E7: Standard Class | F7: BH-11710 | G7: Brosina Hoffman | H7: Consumer | I7: United States | J7: Los Angeles | K7: California | L7: 90032 | M7: West | N7: FUR-FU-10001487 | O7: Furniture | P7: Furnishings | Q7: Eldon Expressions Wood and Plastic Desk Accessories, Cherry Wood | R7: 48.86 | S7: 7 | T7: 0 | U7: 14.1694 | V7: 5 | W7: 2014 | X7: 2014Q2 | Y7: 2014-06 | Z7: 0% (No Discount) | AA7: TRUE | AB7: FALSE | AC7: 6.98 | AD7: 0.29
A8: 7 | B8: CA-2014-115812 | C8: 2014-06-09 | D8: 2014-06-14 | E8: Standard Class | F8: BH-11710 | G8: Brosina Hoffman | H8: Consumer | I8: United States | J8: Los Angeles | K8: California | L8: 90032 | M8: West | N8: OFF-AR-10002833 | O8: Office Supplies | P8: Art | Q8: Newell 322 | R8: 7.28 | S8: 4 | T8: 0 | U8: 1.9656 | V8: 5 | W8: 2014 | X8: 2014Q2 | Y8: 2014-06 | Z8: 0% (No Discount) | AA8: TRUE | AB8: FALSE | AC8: 1.82 | AD8: 0.27
A9: 8 | B9: CA-2014-115812 | C9: 2014-06-09 | D9: 2014-06-14 | E9: Standard Class | F9: BH-11710 | G9: Brosina Hoffman | H9: Consumer | I9: United States | J9: Los Angeles | K9: California | L9: 90032 | M9: West | N9: TEC-PH-10002275 | O9: Technology | P9: Phones | Q9: Mitel 5320 IP Phone VoIP phone | R9: 907.152 | S9: 6 | T9: 0.2 | U9: 90.7152 | V9: 5 | W9: 2014 | X9: 2014Q2 | Y9: 2014-06 | Z9: 10.1% - 20% | AA9: TRUE | AB9: FALSE | AC9: 188.99 | AD9: 0.1
A10: 9 | B10: CA-2014-115812 | C10: 2014-06-09 | D10: 2014-06-14 | E10: Standard Class | F10: BH-11710 | G10: Brosina Hoffman | H10: Consumer | I10: United States | J10: Los Angeles | K10: California | L10: 90032 | M10: West | N10: OFF-BI-10003910 | O10: Office Supplies | P10: Binders | Q10: DXL Angle-View Binders with Locking Rings by Samsill | R10: 18.504 | S10: 3 | T10: 0.2 | U10: 5.7825 | V10: 5 | W10: 2014 | X10: 2014Q2 | Y10: 2014-06 | Z10: 10.1% - 20% | AA10: TRUE | AB10: FALSE | AC10: 7.71 | AD10: 0.3125
A11: 10 | B11: CA-2014-115812 | C11: 2014-06-09 | D11: 2014-06-14 | E11: Standard Class | F11: BH-11710 | G11: Brosina Hoffman | H11: Consumer | I11: United States | J11: Los Angeles | K11: California | L11: 90032 | M11: West | N11: OFF-AP-10002892 | O11: Office Supplies | P11: Appliances | Q11: Belkin F5C206VTEL 6 Outlet Surge | R11: 114.9 | S11: 5 | T11: 0 | U11: 34.47 | V11: 5 | W11: 2014 | X11: 2014Q2 | Y11: 2014-06 | Z11: 0% (No Discount) | AA11: TRUE | AB11: FALSE | AC11: 22.98 | AD11: 0.3
A12: 11 | B12: CA-2014-115812 | C12: 2014-06-09 | D12: 2014-06-14 | E12: Standard Class | F12: BH-11710 | G12: Brosina Hoffman | H12: Consumer | I12: United States | J12: Los Angeles | K12: California | L12: 90032 | M12: West | N12: FUR-TA-10001539 | O12: Furniture | P12: Tables | Q12: Chromcraft Rectangular Conference Tables | R12: 1706.184 | S12: 9 | T12: 0.2 | U12: 85.3092 | V12: 5 | W12: 2014 | X12: 2014Q2 | Y12: 2014-06 | Z12: 10.1% - 20% | AA12: TRUE | AB12: FALSE | AC12: 236.97 | AD12: 0.05
A13: 12 | B13: CA-2014-115812 | C13: 2014-06-09 | D13: 2014-06-14 | E13: Standard Class | F13: BH-11710 | G13: Brosina Hoffman | H13: Consumer | I13: United States | J13: Los Angeles | K13: California | L13: 90032 | M13: West | N13: TEC-PH-10002033 | O13: Technology | P13: Phones | Q13: Konftel 250 Conference phone - Charcoal black | R13: 911.424 | S13: 4 | T13: 0.2 | U13: 68.3568 | V13: 5 | W13: 2014 | X13: 2014Q2 | Y13: 2014-06 | Z13: 10.1% - 20% | AA13: TRUE | AB13: FALSE | AC13: 284.82 | AD13: 0.075
... A9995: 9994 | B9995: CA-2017-119914 | C9995: 2017-05-04 | D9995: 2017-05-09 | E9995: Second Class | F9995: CC-12220 | G9995: Chris Cortes | H9995: Consumer | I9995: United States | J9995: Westminster | K9995: California | L9995: 92683 | M9995: West | N9995: OFF-AP-10002684 | O9995: Office Supplies | P9995: Appliances | Q9995: Acco 7-Outlet Masterpiece Power Center, Wihtout Fax/Phone Line Protection | R9995: 243.16 | S9995: 2 | T9995: 0 | U9995: 72.948 | V9995: 5 | W9995: 2017 | X9995: 2017Q2 | Y9995: 2017-05 | Z9995: 0% (No Discount) | AA9995: TRUE | AB9995: FALSE | AC9995: 121.58 | AD9995: 0.3

Sheet Category Analysis
A1: Category & Subcategory Profitability Analysis
A2: Formula-driven aggregation verifying subcategory margins and identifying negative-margin lines.
A3: Category | B3: Sub-Category | C3: Net Sales | D3: Net Profit | E3: Profit Margin % | F3: Total Items | G3: Unprofitable Items | H3: % Unprofitable Items
A5: Furniture | B5: Bookcases | C5: =SUMIFS('Order Data'!R$2:R$9995, 'Order Data'!O$2:O$9995, A5, 'Order Data'!P$2:P$9995, B5) | D5: =SUMIFS('Order Data'!U$2:U$9995, 'Order Data'!O$2:O$9995, A5, 'Order Data'!P$2:P$9995, B5) | E5: =IF(C5=0, 0, D5/C5) | F5: =COUNTIFS('Order Data'!O$2:O$9995, A5, 'Order Data'!P$2:P$9995, B5) | G5: =COUNTIFS('Order Data'!O$2:O$9995, A5, 'Order Data'!P$2:P$9995, B5, 'Order Data'!U$2:U$9995, "<0") | H5: =IF(F5=0, 0, G5/F5)
A6: Furniture | B6: Chairs | C6: =SUMIFS('Order Data'!R$2:R$9995, 'Order Data'!O$2:O$9995, A6, 'Order Data'!P$2:P$9995, B6) | D6: =SUMIFS('Order Data'!U$2:U$9995, 'Order Data'!O$2:O$9995, A6, 'Order Data'!P$2:P$9995, B6) | E6: =IF(C6=0, 0, D6/C6) | F6: =COUNTIFS('Order Data'!O$2:O$9995, A6, 'Order Data'!P$2:P$9995, B6) | G6: =COUNTIFS('Order Data'!O$2:O$9995, A6, 'Order Data'!P$2:P$9995, B6, 'Order Data'!U$2:U$9995, "<0") | H6: =IF(F6=0, 0, G6/F6)
A7: Furniture | B7: Furnishings | C7: =SUMIFS('Order Data'!R$2:R$9995, 'Order Data'!O$2:O$9995, A7, 'Order Data'!P$2:P$9995, B7) | D7: =SUMIFS('Order Data'!U$2:U$9995, 'Order Data'!O$2:O$9995, A7, 'Order Data'!P$2:P$9995, B7) | E7: =IF(C7=0, 0, D7/C7) | F7: =COUNTIFS('Order Data'!O$2:O$9995, A7, 'Order Data'!P$2:P$9995, B7) | G7: =COUNTIFS('Order Data'!O$2:O$9995, A7, 'Order Data'!P$2:P$9995, B7, 'Order Data'!U$2:U$9995, "<0") | H7: =IF(F7=0, 0, G7/F7)
A8: Furniture | B8: Tables | C8: =SUMIFS('Order Data'!R$2:R$9995, 'Order Data'!O$2:O$9995, A8, 'Order Data'!P$2:P$9995, B8) | D8: =SUMIFS('Order Data'!U$2:U$9995, 'Order Data'!O$2:O$9995, A8, 'Order Data'!P$2:P$9995, B8) | E8: =IF(C8=0, 0, D8/C8) | F8: =COUNTIFS('Order Data'!O$2:O$9995, A8, 'Order Data'!P$2:P$9995, B8) | G8: =COUNTIFS('Order Data'!O$2:O$9995, A8, 'Order Data'!P$2:P$9995, B8, 'Order Data'!U$2:U$9995, "<0") | H8: =IF(F8=0, 0, G8/F8)
A9: Office Supplies | B9: Appliances | C9: =SUMIFS('Order Data'!R$2:R$9995, 'Order Data'!O$2:O$9995, A9, 'Order Data'!P$2:P$9995, B9) | D9: =SUMIFS('Order Data'!U$2:U$9995, 'Order Data'!O$2:O$9995, A9, 'Order Data'!P$2:P$9995, B9) | E9: =IF(C9=0, 0, D9/C9) | F9: =COUNTIFS('Order Data'!O$2:O$9995, A9, 'Order Data'!P$2:P$9995, B9) | G9: =COUNTIFS('Order Data'!O$2:O$9995, A9, 'Order Data'!P$2:P$9995, B9, 'Order Data'!U$2:U$9995, "<0") | H9: =IF(F9=0, 0, G9/F9)
A10: Office Supplies | B10: Art | C10: =SUMIFS('Order Data'!R$2:R$9995, 'Order Data'!O$2:O$9995, A10, 'Order Data'!P$2:P$9995, B10) | D10: =SUMIFS('Order Data'!U$2:U$9995, 'Order Data'!O$2:O$9995, A10, 'Order Data'!P$2:P$9995, B10) | E10: =IF(C10=0, 0, D10/C10) | F10: =COUNTIFS('Order Data'!O$2:O$9995, A10, 'Order Data'!P$2:P$9995, B10) | G10: =COUNTIFS('Order Data'!O$2:O$9995, A10, 'Order Data'!P$2:P$9995, B10, 'Order Data'!U$2:U$9995, "<0") | H10: =IF(F10=0, 0, G10/F10)
A11: Office Supplies | B11: Binders | C11: =SUMIFS('Order Data'!R$2:R$9995, 'Order Data'!O$2:O$9995, A11, 'Order Data'!P$2:P$9995, B11) | D11: =SUMIFS('Order Data'!U$2:U$9995, 'Order Data'!O$2:O$9995, A11, 'Order Data'!P$2:P$9995, B11) | E11: =IF(C11=0, 0, D11/C11) | F11: =COUNTIFS('Order Data'!O$2:O$9995, A11, 'Order Data'!P$2:P$9995, B11) | G11: =COUNTIFS('Order Data'!O$2:O$9995, A11, 'Order Data'!P$2:P$9995, B11, 'Order Data'!U$2:U$9995, "<0") | H11: =IF(F11=0, 0, G11/F11)
A12: Office Supplies | B12: Envelopes | C12: =SUMIFS('Order Data'!R$2:R$9995, 'Order Data'!O$2:O$9995, A12, 'Order Data'!P$2:P$9995, B12) | D12: =SUMIFS('Order Data'!U$2:U$9995, 'Order Data'!O$2:O$9995, A12, 'Order Data'!P$2:P$9995, B12) | E12: =IF(C12=0, 0, D12/C12) | F12: =COUNTIFS('Order Data'!O$2:O$9995, A12, 'Order Data'!P$2:P$9995, B12) | G12: =COUNTIFS('Order Data'!O$2:O$9995, A12, 'Order Data'!P$2:P$9995, B12, 'Order Data'!U$2:U$9995, "<0") | H12: =IF(F12=0, 0, G12/F12)
A13: Office Supplies | B13: Fasteners | C13: =SUMIFS('Order Data'!R$2:R$9995, 'Order Data'!O$2:O$9995, A13, 'Order Data'!P$2:P$9995, B13) | D13: =SUMIFS('Order Data'!U$2:U$9995, 'Order Data'!O$2:O$9995, A13, 'Order Data'!P$2:P$9995, B13) | E13: =IF(C13=0, 0, D13/C13) | F13: =COUNTIFS('Order Data'!O$2:O$9995, A13, 'Order Data'!P$2:P$9995, B13) | G13: =COUNTIFS('Order Data'!O$2:O$9995, A13, 'Order Data'!P$2:P$9995, B13, 'Order Data'!U$2:U$9995, "<0") | H13: =IF(F13=0, 0, G13/F13)
A14: Office Supplies | B14: Labels | C14: =SUMIFS('Order Data'!R$2:R$9995, 'Order Data'!O$2:O$9995, A14, 'Order Data'!P$2:P$9995, B14) | D14: =SUMIFS('Order Data'!U$2:U$9995, 'Order Data'!O$2:O$9995, A14, 'Order Data'!P$2:P$9995, B14) | E14: =IF(C14=0, 0, D14/C14) | F14: =COUNTIFS('Order Data'!O$2:O$9995, A14, 'Order Data'!P$2:P$9995, B14) | G14: =COUNTIFS('Order Data'!O$2:O$9995, A14, 'Order Data'!P$2:P$9995, B14, 'Order Data'!U$2:U$9995, "<0") | H14: =IF(F14=0, 0, G14/F14)
A15: Office Supplies | B15: Paper | C15: =SUMIFS('Order Data'!R$2:R$9995, 'Order Data'!O$2:O$9995, A15, 'Order Data'!P$2:P$9995, B15) | D15: =SUMIFS('Order Data'!U$2:U$9995, 'Order Data'!O$2:O$9995, A15, 'Order Data'!P$2:P$9995, B15) | E15: =IF(C15=0, 0, D15/C15) | F15: =COUNTIFS('Order Data'!O$2:O$9995, A15, 'Order Data'!P$2:P$9995, B15) | G15: =COUNTIFS('Order Data'!O$2:O$9995, A15, 'Order Data'!P$2:P$9995, B15, 'Order Data'!U$2:U$9995, "<0") | H15: =IF(F15=0, 0, G15/F15)
A16: Office Supplies | B16: Storage | C16: =SUMIFS('Order Data'!R$2:R$9995, 'Order Data'!O$2:O$9995, A16, 'Order Data'!P$2:P$9995, B16) | D16: =SUMIFS('Order Data'!U$2:U$9995, 'Order Data'!O$2:O$9995, A16, 'Order Data'!P$2:P$9995, B16) | E16: =IF(C16=0, 0, D16/C16) | F16: =COUNTIFS('Order Data'!O$2:O$9995, A16, 'Order Data'!P$2:P$9995, B16) | G16: =COUNTIFS('Order Data'!O$2:O$9995, A16, 'Order Data'!P$2:P$9995, B16, 'Order Data'!U$2:U$9995, "<0") | H16: =IF(F16=0, 0, G16/F16)
... A21: Technology | B21: Phones | C21: =SUMIFS('Order Data'!R$2:R$9995, 'Order Data'!O$2:O$9995, A21, 'Order Data'!P$2:P$9995, B21) | D21: =SUMIFS('Order Data'!U$2:U$9995, 'Order Data'!O$2:O$9995, A21, 'Order Data'!P$2:P$9995, B21) | E21: =IF(C21=0, 0, D21/C21) | F21: =COUNTIFS('Order Data'!O$2:O$9995, A21, 'Order Data'!P$2:P$9995, B21) | G21: =COUNTIFS('Order Data'!O$2:O$9995, A21, 'Order Data'!P$2:P$9995, B21, 'Order Data'!U$2:U$9995, "<0") | H21: =IF(F21=0, 0, G21/F21)
A22: TOTAL COMPANY | B22: All Subcategories | C22: =SUM(C5:C21) | D22: =SUM(D5:D21) | E22: =IF(C22=0, 0, D22/C22) | F22: =SUM(F5:F21) | G22: =SUM(G5:G21) | H22: =IF(F22=0, 0, G22/F22)

Sheet Discount Analysis
A1: Discount Tier Analysis & Breakeven Cliff
A2: Evaluates margin decay and loss item concentration across discount bands.
A3: Discount Band | B3: Line Items (n) | C3: Net Sales | D3: Net Profit | E3: Profit Margin % | F3: Unprofitable Items | G3: % Unprofitable Items | H3: Total Loss Dollars
A5: 0% (No Discount) | B5: =COUNTIF('Order Data'!Z$2:Z$9995, A5) | C5: =SUMIF('Order Data'!Z$2:Z$9995, A5, 'Order Data'!R$2:R$9995) | D5: =SUMIF('Order Data'!Z$2:Z$9995, A5, 'Order Data'!U$2:U$9995) | E5: =IF(C5=0, 0, D5/C5) | F5: =COUNTIFS('Order Data'!Z$2:Z$9995, A5, 'Order Data'!U$2:U$9995, "<0") | G5: =IF(B5=0, 0, F5/B5) | H5: =SUMIFS('Order Data'!U$2:U$9995, 'Order Data'!Z$2:Z$9995, A5, 'Order Data'!U$2:U$9995, "<0")
A6: 0.1% - 10% | B6: =COUNTIF('Order Data'!Z$2:Z$9995, A6) | C6: =SUMIF('Order Data'!Z$2:Z$9995, A6, 'Order Data'!R$2:R$9995) | D6: =SUMIF('Order Data'!Z$2:Z$9995, A6, 'Order Data'!U$2:U$9995) | E6: =IF(C6=0, 0, D6/C6) | F6: =COUNTIFS('Order Data'!Z$2:Z$9995, A6, 'Order Data'!U$2:U$9995, "<0") | G6: =IF(B6=0, 0, F6/B6) | H6: =SUMIFS('Order Data'!U$2:U$9995, 'Order Data'!Z$2:Z$9995, A6, 'Order Data'!U$2:U$9995, "<0")
A7: 10.1% - 20% | B7: =COUNTIF('Order Data'!Z$2:Z$9995, A7) | C7: =SUMIF('Order Data'!Z$2:Z$9995, A7, 'Order Data'!R$2:R$9995) | D7: =SUMIF('Order Data'!Z$2:Z$9995, A7, 'Order Data'!U$2:U$9995) | E7: =IF(C7=0, 0, D7/C7) | F7: =COUNTIFS('Order Data'!Z$2:Z$9995, A7, 'Order Data'!U$2:U$9995, "<0") | G7: =IF(B7=0, 0, F7/B7) | H7: =SUMIFS('Order Data'!U$2:U$9995, 'Order Data'!Z$2:Z$9995, A7, 'Order Data'!U$2:U$9995, "<0")
A8: 20.1% - 30% | B8: =COUNTIF('Order Data'!Z$2:Z$9995, A8) | C8: =SUMIF('Order Data'!Z$2:Z$9995, A8, 'Order Data'!R$2:R$9995) | D8: =SUMIF('Order Data'!Z$2:Z$9995, A8, 'Order Data'!U$2:U$9995) | E8: =IF(C8=0, 0, D8/C8) | F8: =COUNTIFS('Order Data'!Z$2:Z$9995, A8, 'Order Data'!U$2:U$9995, "<0") | G8: =IF(B8=0, 0, F8/B8) | H8: =SUMIFS('Order Data'!U$2:U$9995, 'Order Data'!Z$2:Z$9995, A8, 'Order Data'!U$2:U$9995, "<0")
A9: 30.1% - 50% | B9: =COUNTIF('Order Data'!Z$2:Z$9995, A9) | C9: =SUMIF('Order Data'!Z$2:Z$9995, A9, 'Order Data'!R$2:R$9995) | D9: =SUMIF('Order Data'!Z$2:Z$9995, A9, 'Order Data'!U$2:U$9995) | E9: =IF(C9=0, 0, D9/C9) | F9: =COUNTIFS('Order Data'!Z$2:Z$9995, A9, 'Order Data'!U$2:U$9995, "<0") | G9: =IF(B9=0, 0, F9/B9) | H9: =SUMIFS('Order Data'!U$2:U$9995, 'Order Data'!Z$2:Z$9995, A9, 'Order Data'!U$2:U$9995, "<0")
A10: > 50% (Deep Discount) | B10: =COUNTIF('Order Data'!Z$2:Z$9995, A10) | C10: =SUMIF('Order Data'!Z$2:Z$9995, A10, 'Order Data'!R$2:R$9995) | D10: =SUMIF('Order Data'!Z$2:Z$9995, A10, 'Order Data'!U$2:U$9995) | E10: =IF(C10=0, 0, D10/C10) | F10: =COUNTIFS('Order Data'!Z$2:Z$9995, A10, 'Order Data'!U$2:U$9995, "<0") | G10: =IF(B10=0, 0, F10/B10) | H10: =SUMIFS('Order Data'!U$2:U$9995, 'Order Data'!Z$2:Z$9995, A10, 'Order Data'!U$2:U$9995, "<0")
A11: TOTAL ALL TIERS | B11: =SUM(B5:B10) | C11: =SUM(C5:C10) | D11: =SUM(D5:D10) | E11: =IF(C11=0, 0, D11/C11) | F11: =SUM(F5:F10) | G11: =IF(B11=0, 0, F11/B11) | H11: =SUM(H5:H10)

Sheet Regional Analysis
A1: Regional Profitability & Geographic Loss Drains
A2: Compares geographic performance and pinpoints top loss-making states.
A4: 1. REGIONAL TERRITORY COMPARISON
A5: Region | B5: Net Sales | C5: Net Profit | D5: Profit Margin % | E5: Total Items | F5: Unprofitable Items | G5: Total Loss Dollars
A6: West | B6: =SUMIF('Order Data'!M$2:M$9995, A6, 'Order Data'!R$2:R$9995) | C6: =SUMIF('Order Data'!M$2:M$9995, A6, 'Order Data'!U$2:U$9995) | D6: =IF(B6=0, 0, C6/B6) | E6: =COUNTIF('Order Data'!M$2:M$9995, A6) | F6: =COUNTIFS('Order Data'!M$2:M$9995, A6, 'Order Data'!U$2:U$9995, "<0") | G6: =SUMIFS('Order Data'!U$2:U$9995, 'Order Data'!M$2:M$9995, A6, 'Order Data'!U$2:U$9995, "<0")
A7: East | B7: =SUMIF('Order Data'!M$2:M$9995, A7, 'Order Data'!R$2:R$9995) | C7: =SUMIF('Order Data'!M$2:M$9995, A7, 'Order Data'!U$2:U$9995) | D7: =IF(B7=0, 0, C7/B7) | E7: =COUNTIF('Order Data'!M$2:M$9995, A7) | F7: =COUNTIFS('Order Data'!M$2:M$9995, A7, 'Order Data'!U$2:U$9995, "<0") | G7: =SUMIFS('Order Data'!U$2:U$9995, 'Order Data'!M$2:M$9995, A7, 'Order Data'!U$2:U$9995, "<0")
A8: South | B8: =SUMIF('Order Data'!M$2:M$9995, A8, 'Order Data'!R$2:R$9995) | C8: =SUMIF('Order Data'!M$2:M$9995, A8, 'Order Data'!U$2:U$9995) | D8: =IF(B8=0, 0, C8/B8) | E8: =COUNTIF('Order Data'!M$2:M$9995, A8) | F8: =COUNTIFS('Order Data'!M$2:M$9995, A8, 'Order Data'!U$2:U$9995, "<0") | G8: =SUMIFS('Order Data'!U$2:U$9995, 'Order Data'!M$2:M$9995, A8, 'Order Data'!U$2:U$9995, "<0")
A9: Central | B9: =SUMIF('Order Data'!M$2:M$9995, A9, 'Order Data'!R$2:R$9995) | C9: =SUMIF('Order Data'!M$2:M$9995, A9, 'Order Data'!U$2:U$9995) | D9: =IF(B9=0, 0, C9/B9) | E9: =COUNTIF('Order Data'!M$2:M$9995, A9) | F9: =COUNTIFS('Order Data'!M$2:M$9995, A9, 'Order Data'!U$2:U$9995, "<0") | G9: =SUMIFS('Order Data'!U$2:U$9995, 'Order Data'!M$2:M$9995, A9, 'Order Data'!U$2:U$9995, "<0")
A12: 2. TOP 5 LOSS-MAKING STATES (HEAVY DISCOUNTING CENTERS)
A13: State | B13: Region | C13: Net Sales | D13: Net Loss Amount | E13: Profit Margin % | F13: Average Discount Rate
A14: Texas | B14: Central | C14: =SUMIF('Order Data'!K$2:K$9995, A14, 'Order Data'!R$2:R$9995) | D14: =SUMIF('Order Data'!K$2:K$9995, A14, 'Order Data'!U$2:U$9995) | E14: =IF(C14=0, 0, D14/C14) | F14: =AVERAGEIF('Order Data'!K$2:K$9995, A14, 'Order Data'!T$2:T$9995)
A15: Ohio | B15: East | C15: =SUMIF('Order Data'!K$2:K$9995, A15, 'Order Data'!R$2:R$9995) | D15: =SUMIF('Order Data'!K$2:K$9995, A15, 'Order Data'!U$2:U$9995) | E15: =IF(C15=0, 0, D15/C15) | F15: =AVERAGEIF('Order Data'!K$2:K$9995, A15, 'Order Data'!T$2:T$9995)
A16: Pennsylvania | B16: East | C16: =SUMIF('Order Data'!K$2:K$9995, A16, 'Order Data'!R$2:R$9995) | D16: =SUMIF('Order Data'!K$2:K$9995, A16, 'Order Data'!U$2:U$9995) | E16: =IF(C16=0, 0, D16/C16) | F16: =AVERAGEIF('Order Data'!K$2:K$9995, A16, 'Order Data'!T$2:T$9995)
A17: Illinois | B17: Central | C17: =SUMIF('Order Data'!K$2:K$9995, A17, 'Order Data'!R$2:R$9995) | D17: =SUMIF('Order Data'!K$2:K$9995, A17, 'Order Data'!U$2:U$9995) | E17: =IF(C17=0, 0, D17/C17) | F17: =AVERAGEIF('Order Data'!K$2:K$9995, A17, 'Order Data'!T$2:T$9995)
A18: Colorado | B18: West | C18: =SUMIF('Order Data'!K$2:K$9995, A18, 'Order Data'!R$2:R$9995) | D18: =SUMIF('Order Data'!K$2:K$9995, A18, 'Order Data'!U$2:U$9995) | E18: =IF(C18=0, 0, D18/C18) | F18: =AVERAGEIF('Order Data'!K$2:K$9995, A18, 'Order Data'!T$2:T$9995)

Sheet Methodology
A1: Analytical Methodology, Data Definitions & Assumptions
A2: Technical reference documentation supporting interview defense and auditability.
A4: 1. Dataset Source & Nature
A5: • Dataset: Tableau Sample - Superstore (United States retail transactions, 2014-2017).
A6: • Nature: Educational and analytics benchmarking dataset distributed historically for business intelligence training.
A7: • Scale: 9,994 line-item transaction records across 5,009 distinct customer orders and 793 customer accounts.
A9: 2. Metric Definitions & Aggregation Rules
A10: • Net Sales: Recorded post-discount transaction revenue collected from the customer.
A11: • Net Profit: Net financial profit after product costs and discounting.
A12: • Profit Margin %: Calculated as SUM(Profit) / SUM(Sales) * 100%. Never calculated as the arithmetic mean of line-item margins (Simpson's paradox prevention).
A13: • Distinct Orders: Counted via unique Order ID (5,009 orders), avoiding double-counting multi-item baskets.
A14: • Net-Sales-Weighted Discount: SUM(Sales * Discount) / SUM(Sales) = 14.04% (reflects net revenue concession).
... A26: • Safe Division: All profit margin formulas employ IF(Sales=0, 0, Profit/Sales) to prevent #DIV/0! errors.
